doomsdaytutor/__init__.py
doomsdaytutor/__main__.py
doomsdaytutor/cli.py
doomsdaytutor/commands.py
doomsdaytutor/dd/__init__.py
doomsdaytutor/dd/const.py
doomsdaytutor/dd/difficulty.py
doomsdaytutor/dd/feedback.py
doomsdaytutor/dd/iox.py
doomsdaytutor/dd/tutor.py
doomsdaytutor-0.2.0.dist-info/LICENSE.txt
doomsdaytutor-0.2.0.dist-info/METADATA
doomsdaytutor-0.2.0.dist-info/WHEEL
doomsdaytutor-0.2.0.dist-info/entry_points.txt
doomsdaytutor-0.2.0.dist-info/top_level.txt
doomsdaytutor-0.2.0.dist-info/RECORD
