Metadata-Version: 2.1
Name: doomsdaytutor
Version: 0.2.0
Summary: Doomsdaytutor - learn the doomsday algorithm fast
Home-page: https://github.com/liamvdv/doomsdaytutor
Author: Liam van der Viven
Author-email: liam.vanderviven@gmx.de
License: MIT
Project-URL: Source, https://github.com/liamvdv/doomsdaytutor/
Project-URL: Documentation, https://github.com/liamvdv/doomsdaytutor/
Platform: UNKNOWN
Classifier: Development Status :: 3 - Alpha
Classifier: Topic :: Education
Classifier: License :: OSI Approved :: MIT License
Classifier: Natural Language :: English
Classifier: Programming Language :: Python
Classifier: Programming Language :: Python :: 3
Classifier: Programming Language :: Python :: 3.6
Requires-Python: >=3.6
License-File: LICENSE.txt
Requires-Dist: colorama (>=0.4.4)
Requires-Dist: inquirerpy (>=0.3.3)
Requires-Dist: babel (>=2.9.1)
